tflwrapper/__init__.py
tflwrapper/accidentStats.py
tflwrapper/airQuality.py
tflwrapper/bikePoint.py
tflwrapper/crowding.py
tflwrapper/disruptions.py
tflwrapper/line.py
tflwrapper/mode.py
tflwrapper/occupancy.py
tflwrapper/road.py
tflwrapper/stopPoint.py
tflwrapper/tfl.py
tflwrapper/trackerNet.py
tflwrapper/travelTimes.py
tflwrapper-1.1.9.dist-info/LICENSE
tflwrapper-1.1.9.dist-info/METADATA
tflwrapper-1.1.9.dist-info/WHEEL
tflwrapper-1.1.9.dist-info/top_level.txt
tflwrapper-1.1.9.dist-info/RECORD
