Metadata-Version: 2.1
Name: tflwrapper
Version: 1.1.9
Summary: A wrapper for the Transport for London Unified API and TrackerNet
Home-page: https://github.com/ZackaryH8/tfl-api-wrapper-py
Author: zackaryh8
Author-email: zackary12389@yahoo.co.uk
License: MIT
License-File: LICENSE
Requires-Dist: xmltodict
